django_extra_fields_lab-0.3.dist-info/DESCRIPTION.rst
django_extra_fields_lab-0.3.dist-info/METADATA
django_extra_fields_lab-0.3.dist-info/RECORD
django_extra_fields_lab-0.3.dist-info/WHEEL
django_extra_fields_lab-0.3.dist-info/metadata.json
django_extra_fields_lab-0.3.dist-info/top_level.txt
drf_extra_fields/__init__.py
drf_extra_fields/fields.py
drf_extra_fields/geo_fields.py
drf_extra_fields/runtests/__init__.py
drf_extra_fields/runtests/runtests.py
drf_extra_fields/runtests/settings.py
drf_extra_fields/runtests/urls.py
