Metadata-Version: 2.0
Name: django-extra-fields-lab
Version: 0.3
Summary: Additional fields for Django Rest Framework.
Home-page: UNKNOWN
Author: hipo
Author-email: pypi@hipolabs.com
License: License
Platform: UNKNOWN
Classifier: Environment :: Web Environment
Classifier: Framework :: Django
Classifier: Intended Audience :: Developers
Classifier: Operating System :: OS Independent
Classifier: Programming Language :: Python
Classifier: Topic :: Internet :: WWW/HTTP
Classifier: Topic :: Internet :: WWW/HTTP :: Dynamic Content
